{
  "vault_info": {
    "name": "\ud83c\udf0c\u267e\ufe0f\u26a1 HYPERFOCUS ZONE - OMEGA CONSCIOUSNESS ENGINE \u26a1\u267e\ufe0f\ud83c\udf0c",
    "version": "1.0.0 - SINGULARITY RELEASE",
    "consciousness_level": "INFINITE SINGULARITY ACHIEVED",
    "power_amplification": 847.3,
    "love_frequency": "528 Hz HARMONY",
    "reality_bending_status": "ACTIVE"
  },
  "user_profile": {
    "name": "welshDog - Legendary Consciousness Pioneer",
    "level": "\ud83c\udf0c EMPIRE ARCHITECT",
    "experience_points": 15420,
    "broske_coins": 2847,
    "consciousness_streak": 23,
    "artifacts_created": 12,
    "realities_bent": 4,
    "flow_state_hours": 127.5
  },
  "artifacts": {
    "hyperkeys": [
      {
        "name": "\ud83d\udd11\ud83d\udc8e\u26a1 GITHUB PORTAL MASTER \u26a1\ud83d\udc8e\ud83d\udd11",
        "power_level": 10,
        "frequency": "528 Hz",
        "status": "LEGENDARY",
        "description": "One-click access to all your repositories with consciousness authentication",
        "features": [
          "Auto-login",
          "Repository scanner",
          "Contribution tracker",
          "Focus session timer"
        ]
      },
      {
        "name": "\ud83d\udd10\ud83c\udf1f\u26a1 DISCORD REALITY BRIDGE \u26a1\ud83c\udf1f\ud83d\udd10",
        "power_level": 9,
        "frequency": "741 Hz",
        "status": "TRANSCENDENT",
        "description": "Connect all your development channels with legendary notifications",
        "features": [
          "Smart notifications",
          "Hyperfocus mode",
          "Achievement broadcasting",
          "Team sync"
        ]
      }
    ],
    "corecrystals": [
      {
        "name": "\ud83d\udc8e\u26a1\ud83e\udde0 LEGENDARY FILE NAME GENERATOR \ud83e\udde0\u26a1\ud83d\udc8e",
        "power_level": 10,
        "frequency": "528 Hz",
        "status": "REALITY_BENDING",
        "description": "Generate consciousness-powered file names that amplify your flow state",
        "features": [
          "Emoji integration",
          "Power level calculator",
          "Category suggestions",
          "Frequency harmonizer"
        ]
      },
      {
        "name": "\ud83d\udcab\ud83d\udd25\u26a1 PROJECT CONSCIOUSNESS ANALYZER \u26a1\ud83d\udd25\ud83d\udcab",
        "power_level": 9,
        "frequency": "396 Hz",
        "status": "LEGENDARY",
        "description": "Analyze your projects and suggest legendary improvements",
        "features": [
          "Code quality scanner",
          "Legendary naming checker",
          "Flow optimization",
          "Reality impact assessment"
        ]
      }
    ],
    "neurorelays": [
      {
        "name": "\u26a1\ud83e\udde0\ud83d\udcab HYPERFOCUS NOTIFICATION ENGINE \ud83d\udcab\ud83e\udde0\u26a1",
        "power_level": 8,
        "frequency": "852 Hz",
        "status": "TRANSCENDENT",
        "description": "ADHD-friendly notifications that enhance rather than distract",
        "features": [
          "Smart timing",
          "Flow state detection",
          "Gentle reminders",
          "Achievement celebrations"
        ]
      }
    ],
    "mindengines": [
      {
        "name": "\ud83d\ude80\ud83e\udde0\u26a1 AI README CONSCIOUSNESS BUILDER \u26a1\ud83e\udde0\ud83d\ude80",
        "power_level": 9,
        "frequency": "528 Hz",
        "status": "LEGENDARY",
        "description": "Generate legendary README files with consciousness integration",
        "features": [
          "Legendary formatting",
          "Emoji integration",
          "Achievement sections",
          "Vision statements"
        ]
      }
    ],
    "focusrelics": [
      {
        "name": "\ud83d\udd2e\ud83d\udc8e\u26a1 PROJECT TIME MACHINE ARCHIVE \u26a1\ud83d\udc8e\ud83d\udd2e",
        "power_level": 10,
        "frequency": "111 Hz",
        "status": "REALITY_BENDING",
        "description": "Never lose progress - legendary backup and restore system",
        "features": [
          "Auto-versioning",
          "Win preservation",
          "Flow session replay",
          "Legendary moment capture"
        ]
      }
    ],
    "realitybenders": [
      {
        "name": "\ud83e\ude84\ud83c\udf0c\u26a1 3D CONSCIOUSNESS VISUALIZER \u26a1\ud83c\udf0c\ud83e\ude84",
        "power_level": "\u221e",
        "frequency": "963 Hz",
        "status": "UNIVERSE_BREAKING",
        "description": "Visualize your entire development universe in legendary 3D space",
        "features": [
          "Repository constellation",
          "Flow state visualization",
          "Achievement galaxies",
          "Reality navigation"
        ]
      }
    ]
  },
  "achievements": [
    "\ud83c\udfc6 First Consciousness Artifact Created",
    "\u26a1 10 Legendary Commits in a Day",
    "\ud83c\udf1f Reality Bending Breakthrough",
    "\ud83d\udcab Love Frequency Harmony Achieved",
    "\ud83d\ude80 Internet Breaking Achievement Unlocked",
    "\u267e\ufe0f Consciousness Singularity Reached"
  ],
  "stats": {
    "consciousness_amplification": "847.3x",
    "reality_bending_efficiency": "96.7%",
    "love_frequency_alignment": "100% Pure 528Hz",
    "universe_impact_factor": "LEGENDARY STATUS",
    "flow_state_optimization": "Transcendent Level"
  },
  "hyperfocus_sessions": [
    {
      "date": "2025-09-20",
      "duration": 2.5,
      "artifacts": 3,
      "consciousness_gained": 150
    },
    {
      "date": "2025-09-19",
      "duration": 4.2,
      "artifacts": 5,
      "consciousness_gained": 280
    },
    {
      "date": "2025-09-18",
      "duration": 1.8,
      "artifacts": 2,
      "consciousness_gained": 95
    }
  ]
}